package_twitter/__init__.py
package_twitter/cli.py
package_twitter/tweet.py
package_twitter-0.1.5.dist-info/LICENSE
package_twitter-0.1.5.dist-info/METADATA
package_twitter-0.1.5.dist-info/WHEEL
package_twitter-0.1.5.dist-info/entry_points.txt
package_twitter-0.1.5.dist-info/RECORD
