Metadata-Version: 2.3
Name: package-twitter
Version: 0.1.5
Summary: a lightweight Python package designed to simplify programmatic tweeting on Twitter
Author: Nivesh03
Author-email: niveshsharma67@gmail.com
Requires-Python: >=3.11
Classifier: Programming Language :: Python :: 3
Classifier: Programming Language :: Python :: 3.11
Classifier: Programming Language :: Python :: 3.12
Classifier: Programming Language :: Python :: 3.13
Requires-Dist: tweepy (>=4.15.0,<5.0.0)
